{
  "main": {
    "id": "c907d4c92a4f7367",
    "type": "split",
    "children": [
      {
        "id": "dc646231e940bd8a",
        "type": "tabs",
        "children": [
          {
            "id": "aa371510607e06b2",
            "type": "leaf",
            "state": {
              "type": "canvas",
              "state": {
                "file": "Untitled.canvas",
                "viewState": {
                  "x": 0,
                  "y": 0,
                  "zoom": 0
                }
              },
              "icon": "lucide-layout-dashboard",
              "title": "Untitled"
            }
          }
        ]
      }
    ],
    "direction": "vertical"
  },
  "left": {
    "id": "529e560c61e3e166",
    "type": "split",
    "children": [
      {
        "id": "5269857ef951b099",
        "type": "tabs",
        "children": [
          {
            "id": "2ed714bbec86aa92",
            "type": "leaf",
            "state": {
              "type": "file-explorer",
              "state": {
                "sortOrder": "alphabetical",
                "autoReveal": false
              },
              "icon": "lucide-folder-closed",
              "title": "Files"
            }
          },
          {
            "id": "90a3cef6cb814747",
            "type": "leaf",
            "state": {
              "type": "search",
              "state": {
                "query": "",
                "matchingCase": false,
                "explainSearch": false,
                "collapseAll": false,
                "extraContext": false,
                "sortOrder": "alphabetical"
              },
              "icon": "lucide-search",
              "title": "Search"
            }
          },
          {
            "id": "98376b2c1848a6f7",
            "type": "leaf",
            "state": {
              "type": "bookmarks",
              "state": {},
              "icon": "lucide-bookmark",
              "title": "Bookmarks"
            }
          }
        ]
      }
    ],
    "direction": "horizontal",
    "width": 300
  },
  "right": {
    "id": "e440af8963c6b7fa",
    "type": "split",
    "children": [
      {
        "id": "0b9dd3e002e60ad4",
        "type": "tabs",
        "children": [
          {
            "id": "3da7f424fd48100c",
            "type": "leaf",
            "state": {
              "type": "backlink",
              "state": {
                "collapseAll": false,
                "extraContext": false,
                "sortOrder": "alphabetical",
                "showSearch": false,
                "searchQuery": "",
                "backlinkCollapsed": false,
                "unlinkedCollapsed": true
              },
              "icon": "links-coming-in",
              "title": "Backlinks"
            }
          },
          {
            "id": "1cb82e0e500887d8",
            "type": "leaf",
            "state": {
              "type": "outgoing-link",
              "state": {
                "linksCollapsed": false,
                "unlinkedCollapsed": true
              },
              "icon": "links-going-out",
              "title": "Outgoing links"
            }
          },
          {
            "id": "55c3ce8b27a11455",
            "type": "leaf",
            "state": {
              "type": "tag",
              "state": {
                "sortOrder": "frequency",
                "useHierarchy": true,
                "showSearch": false,
                "searchQuery": ""
              },
              "icon": "lucide-tags",
              "title": "Tags"
            }
          },
          {
            "id": "3a687de76088895a",
            "type": "leaf",
            "state": {
              "type": "all-properties",
              "state": {
                "sortOrder": "frequency",
                "showSearch": false,
                "searchQuery": ""
              },
              "icon": "lucide-archive",
              "title": "All properties"
            }
          },
          {
            "id": "68473b1964dd0b05",
            "type": "leaf",
            "state": {
              "type": "outline",
              "state": {
                "followCursor": false,
                "showSearch": false,
                "searchQuery": ""
              },
              "icon": "lucide-list",
              "title": "Outline"
            }
          }
        ]
      }
    ],
    "direction": "horizontal",
    "width": 300,
    "collapsed": true
  },
  "left-ribbon": {
    "hiddenItems": {
      "switcher:Open quick switcher": false,
      "graph:Open graph view": false,
      "canvas:Create new canvas": false,
      "daily-notes:Open today's daily note": false,
      "templates:Insert template": false,
      "command-palette:Open command palette": false,
      "bases:Create new base": false
    }
  },
  "active": "aa371510607e06b2",
  "lastOpenFiles": [
    "Untitled 2.canvas",
    "2026-02-05.md",
    "2026-01-25.md",
    "DNS (Domain name System).md",
    "Untitled.canvas",
    "Untitled.base",
    "Untitled 1.canvas",
    "linux.md"
  ]
}